mode/__init__.py
mode/debug.py
mode/exceptions.py
mode/locals.py
mode/proxy.py
mode/py.typed
mode/services.py
mode/signals.py
mode/supervisors.py
mode/threads.py
mode/timers.py
mode/worker.py
mode/loop/__init__.py
mode/loop/_gevent_loop.py
mode/loop/eventlet.py
mode/loop/gevent.py
mode/loop/uvloop.py
mode/types/__init__.py
mode/types/services.py
mode/types/signals.py
mode/types/supervisors.py
mode/utils/__init__.py
mode/utils/aiter.py
mode/utils/collections.py
mode/utils/compat.py
mode/utils/contexts.py
mode/utils/cron.py
mode/utils/futures.py
mode/utils/imports.py
mode/utils/locals.py
mode/utils/locks.py
mode/utils/logging.py
mode/utils/loops.py
mode/utils/mocks.py
mode/utils/objects.py
mode/utils/queues.py
mode/utils/text.py
mode/utils/times.py
mode/utils/tracebacks.py
mode/utils/trees.py
mode/utils/graphs/__init__.py
mode/utils/graphs/formatter.py
mode/utils/graphs/graph.py
mode/utils/types/__init__.py
mode/utils/types/graphs.py
mode/utils/types/trees.py
mode_continued-1.0.0.dist-info/licenses/AUTHORS
mode_continued-1.0.0.dist-info/licenses/LICENSE
mode_continued-1.0.0.dist-info/METADATA
mode_continued-1.0.0.dist-info/WHEEL
mode_continued-1.0.0.dist-info/top_level.txt
mode_continued-1.0.0.dist-info/RECORD
